pypi_test/__init__.py
pypi_test/gfg.py
vibhu4gfg_test_simojoe-1.0.1.dist-info/METADATA
vibhu4gfg_test_simojoe-1.0.1.dist-info/WHEEL
vibhu4gfg_test_simojoe-1.0.1.dist-info/entry_points.txt
vibhu4gfg_test_simojoe-1.0.1.dist-info/top_level.txt
vibhu4gfg_test_simojoe-1.0.1.dist-info/RECORD
