Metadata-Version: 2.1
Name: vibhu4gfg-test-simojoe
Version: 1.0.1
Summary: Demo Package for GfG Article.
Home-page: https://github.com/Vibhu-Agarwal/vibhu4gfg
Author: Vibhu Agarwal
Author-email: joel.simoneau@usherbrooke.ca
License: MIT
Keywords: geeksforgeeks gfg article python package vibhu4agarwal
Platform: UNKNOWN
Classifier: Programming Language :: Python :: 3
Classifier: License :: OSI Approved :: MIT License
Classifier: Operating System :: OS Independent
Requires-Dist: numpy (>=1.18)
